Metadata-Version: 1.0
Name: STA-distributions
Version: 0.2
Summary: Gaussian and Binomial distributions
Home-page: UNKNOWN
Author: Sloan Austermann
Author-email: UNKNOWN
License: UNKNOWN
Platform: UNKNOWN
